qbzstoredl/__init__.py
qbzstoredl-0.1.2.dist-info/LICENSE
qbzstoredl-0.1.2.dist-info/METADATA
qbzstoredl-0.1.2.dist-info/WHEEL
qbzstoredl-0.1.2.dist-info/entry_points.txt
qbzstoredl-0.1.2.dist-info/RECORD
