Metadata-Version: 2.1
Name: qbzstoredl
Version: 0.1.2
Summary: Downloader for music from the Qobuz download store
Home-page: https://gitlab.com/pkerling/qbzstoredl
License: GPL-3.0-or-later
Author: Philipp Kerling
Author-email: pip@casix.org
Requires-Python: >=3.10,<4.0
Classifier: Development Status :: 3 - Alpha
Classifier: Environment :: Console
Classifier: License :: OSI Approved :: GNU General Public License v3 or later (GPLv3+)
Classifier: Programming Language :: Python :: 3
Classifier: Programming Language :: Python :: 3.10
Classifier: Programming Language :: Python :: 3.11
Classifier: Programming Language :: Python :: 3.12
Classifier: Topic :: Internet :: WWW/HTTP
Classifier: Topic :: Multimedia :: Sound/Audio
Classifier: Topic :: Utilities
Requires-Dist: ffpb (>=0.4.1,<0.5.0)
Requires-Dist: httpx (>=0.27.0,<0.28.0)
Requires-Dist: mutagen (>=1.47.0,<2.0.0)
Requires-Dist: pathvalidate (>=3.2.0,<4.0.0)
Requires-Dist: pillow (>=10.1.0,<11.0.0)
Requires-Dist: requests (>=2.31.0,<3.0.0)
Requires-Dist: tqdm (>=4.66.1,<5.0.0)
Project-URL: Repository, https://gitlab.com/pkerling/qbzstoredl
